ciberc_l3vpn_notify/__init__.py
ciberc_l3vpn_notify/configure.py
ciberc_l3vpn_notify/core.py
ciberc_l3vpn_notify/main.py
ciberc_l3vpn_notify/notify.py
ciberc_l3vpn_notify/reflector.py
ciberc_l3vpn_notify/rollback.py
ciberc_l3vpn_notify/templates/config-templates/huawei_vrp.j2
ciberc_l3vpn_notify/templates/config-templates/ios.j2
ciberc_l3vpn_notify/templates/config-templates/iosxr.j2
ciberc_l3vpn_notify/templates/config-templates/junos.j2
ciberc_l3vpn_notify/templates/rollback-templates/huawei_vrp.j2
ciberc_l3vpn_notify/templates/rollback-templates/ios.j2
ciberc_l3vpn_notify/templates/rollback-templates/iosxr.j2
ciberc_l3vpn_notify/templates/rollback-templates/junos.j2
ciberc_l3vpn_notify-0.1.1.dist-info/METADATA
ciberc_l3vpn_notify-0.1.1.dist-info/WHEEL
ciberc_l3vpn_notify-0.1.1.dist-info/entry_points.txt
ciberc_l3vpn_notify-0.1.1.dist-info/top_level.txt
ciberc_l3vpn_notify-0.1.1.dist-info/RECORD
