Metadata-Version: 2.1
Name: ciberc-l3vpn-notify
Version: 0.1.1
Summary: CiberC Automated Cases
Author: Rafael Fernando Garcia Sagastume
Requires-Dist: nornir (==3.3.0)
Requires-Dist: nornir-jinja2 (==0.2.0)
Requires-Dist: nornir-netmiko (==1.0.0)
Requires-Dist: nornir-napalm (==0.4.0)
Requires-Dist: nornir-utils (==0.2.0)
Requires-Dist: napalm (==4.1.0)
Requires-Dist: napalm-huawei-vrp (==1.1.0)
Requires-Dist: typer (==0.9.0)
Requires-Dist: setuptools (==68.0.0)
Requires-Dist: wheel (==0.41.0)
Requires-Dist: webexteamsbot (==0.1.4.2)
Requires-Dist: tqdm (==4.65.0)
Requires-Dist: pylint (==2.17.5)
